etos_client/__init__.py
etos_client/__main__.py
etos_client/command.py
etos_client/etos/v0/__init__.py
etos_client/etos/v0/command.py
etos_client/etos/v0/etos.py
etos_client/etos/v0/event_repository/__init__.py
etos_client/etos/v0/event_repository/graphql.py
etos_client/etos/v0/event_repository/graphql_queries.py
etos_client/etos/v0/events/__init__.py
etos_client/etos/v0/events/collector.py
etos_client/etos/v0/events/events.py
etos_client/etos/v0/schema/__init__.py
etos_client/etos/v0/schema/request.py
etos_client/etos/v0/schema/response.py
etos_client/etos/v0/subcommands/__init__.py
etos_client/etos/v0/subcommands/start.py
etos_client/etos/v0/test_results/__init__.py
etos_client/etos/v0/test_results/test_results.py
etos_client/etos/v0/test_run/__init__.py
etos_client/etos/v0/test_run/test_run.py
etos_client/etos/v1alpha/__init__.py
etos_client/etos/v1alpha/command.py
etos_client/etos/v1alpha/etos.py
etos_client/etos/v1alpha/schema/__init__.py
etos_client/etos/v1alpha/schema/request.py
etos_client/etos/v1alpha/schema/response.py
etos_client/etos/v1alpha/subcommands/__init__.py
etos_client/etos/v1alpha/subcommands/start.py
etos_client/etos/v1alpha/test_run/__init__.py
etos_client/etos/v1alpha/test_run/test_run.py
etos_client/shared/__init__.py
etos_client/shared/downloader.py
etos_client/shared/events.py
etos_client/shared/utilities.py
etos_client/sse/__init__.py
etos_client/sse/v1/__init__.py
etos_client/sse/v1/client.py
etos_client/sse/v1/protocol.py
etos_client/sse/v2alpha/__init__.py
etos_client/sse/v2alpha/client.py
etos_client/types/result.py
etos_debug/__init__.py
etos_debug/command.py
etosctl/__init__.py
etosctl/__main__.py
etosctl/command/__init__.py
etosctl/command/command.py
etosctl/engine/__init__.py
etosctl/engine/engine.py
etosctl/models/__init__.py
etosctl/models/models.py
etosctl/options/__init__.py
etosctl/options/options.py
etos_client-7.3.0.dist-info/METADATA
etos_client-7.3.0.dist-info/WHEEL
etos_client-7.3.0.dist-info/entry_points.txt
etos_client-7.3.0.dist-info/top_level.txt
etos_client-7.3.0.dist-info/RECORD
