Metadata-Version: 2.4
Name: etos_client
Version: 7.3.0
Summary: Test suite execution client for ETOS.
Author-email: Tobias Persson <tobias.persson@axis.com>
License: Apache License, Version 2.0
Project-URL: Documentation, https://etos.readthedocs.io/
Project-URL: Homepage, https://github.com/eiffel-community/etos
Project-URL: Repository, https://github.com/eiffel-community/etos
Classifier: Development Status :: 4 - Beta
Classifier: Programming Language :: Python :: 3
Classifier: License :: OSI Approved :: Apache Software License
Requires-Python: >=3.9
Requires-Dist: etos_lib==5.1.4
Requires-Dist: docopt~=0.6
Requires-Dist: pydantic~=2.6
Provides-Extra: testing
Requires-Dist: pytest; extra == "testing"
Requires-Dist: pytest-cov; extra == "testing"
